status_600/__init__.py
status_600/module.MD
status_600/module.s.HTML
status_600/names.s.HTML
status_600/procedure.proc.py
status_600/__book/codesweeper--ai-generated-8311435_1920.jpg
status_600/__book/codesweeper--ai-generated-8311446_1920.jpg
status_600/__book/codesweeper--ai-generated-8311450_1920.jpg
status_600/__license/license.s.HTML
status_600/__license/options/gpl-3.0-standalone.html
status_600/_clique/__init__.py
status_600/_clique/group/__init__.py
status_600/_status/__init__.py
status_600/_status/status.proc.py
status_600/_status/_stories/story_instrument_1/status_1.py
status_600/instrument/__init__.py
status_600/instrument/module--names.s.HTML
status_600/instrument/start.proc.py
status_600/instrument/__agenda/agenda.s.HTML
status_600/instrument/__book/TheDigitalArtist--ai-generated-8228359_1920.jpg
status_600/instrument/__book/TheDigitalArtist--ai-generated-8228360_1920.jpg
status_600/instrument/__book/dlsdkcgl--hidden-8315722_1920.jpg
status_600/instrument/__book/_hardware/hardware.s.HTML
status_600/instrument/__book/_hardware/ISO/ISO_lab.s.HTML
status_600/instrument/__book/_hardware/ISO/ISO_lab_2.s.HTML
status_600/instrument/__book/_hardware/ISO/write_ISO_to_drive.py
status_600/instrument/__book/_hardware/docker/docker.s.HTML
status_600/instrument/__book/_hardware/docker/essential_installations.s.HTML
status_600/instrument/__book/_hardware/docker/compose/compose.s.HTML
status_600/instrument/__book/_hardware/docker/containers/containers.s.HTML
status_600/instrument/__book/_hardware/docker/containers/installations.s.HTML
status_600/instrument/__book/_hardware/docker/images/images.s.HTML
status_600/instrument/_status/status_1.py
status_600/instrument/climate/__init__.py
status_600/instrument/clique/__init__.py
status_600/instrument/frontend/codesweeper--ai-generated-8311446_1920.jpg
status_600/instrument/frontend/index.html
status_600/instrument/frontend/assets/feel-1b84c382.js
status_600/instrument/frontend/assets/futon-180affc4.js
status_600-1.0.2.dist-info/METADATA
status_600-1.0.2.dist-info/WHEEL
status_600-1.0.2.dist-info/entry_points.txt
status_600-1.0.2.dist-info/top_level.txt
status_600-1.0.2.dist-info/RECORD
